kine/__about__.py
kine/__init__.py
kine-0.0.1.dist-info/METADATA
kine-0.0.1.dist-info/WHEEL
kine-0.0.1.dist-info/licenses/LICENSE.txt
kine-0.0.1.dist-info/RECORD
